[
	{
		"id": "2015_F1_driver",
		"name": "Ranking Driver",
		"displayName": "Classement Pilotes",
		"orderDisplay": 1,
		"teams": [
			{
				"id": "",
				"displayName": "Lewis Hamilton",
				"imageUrl": "",
				"rang": "1er",
				"position": 1,
				"points": {
					"total": 252,
					"blegique": 25,
					"canada": 25,
					"italie": 25,
					"singapour": 18,
					"russie": 25,
					"monaco": 18,
					"barhein": 25,
					"abudhabi": 25,				
				},
				"promotion": "NOT USED"
			},
			{
				"id": "",
				"displayName": "Nico Roseberg",
				"imageUrl": "",
				"rang": "2e",
				"position": 2,
				"points": {
					"total": 252,
					"blegique": 25,
					"canada": 25,
					"italie": 25,
					"singapour": 18,
					"russie": 25,
					"monaco": 18,
					"barhein": 25,
					"abudhabi": 25,				
				},
				"promotion": "NOT USED"
			},
			{
				"id": "",
				"displayName": "Sebastian Vettel",
				"imageUrl": "",
				"rang": "3e",
				"position": 3,
				"points": {
					"total": 252,
					"blegique": 25,
					"canada": 25,
					"italie": 25,
					"singapour": 18,
					"russie": 25,
					"monaco": 18,
					"barhein": 25,
					"abudhabi": 25,				
				},
				"promotion": "NOT USED"
			},
			{
				"id": "",
				"displayName": "Valteri Bottas",
				"imageUrl": "",
				"rang": "4e",
				"position": 4,
				"points": {
					"total": 252,
					"blegique": 25,
					"canada": 25,
					"italie": 25,
					"singapour": 18,
					"russie": 25,
					"monaco": 18,
					"barhein": 25,
					"abudhabi": 25,				
				},
				"promotion": "NOT USED"
			},
			{
				"id": "",
				"displayName": "Kimi Raikkonen",
				"imageUrl": "",
				"rang": "5e",
				"position": 5,
				"points": {
					"total": 252,
					"blegique": 25,
					"canada": 25,
					"italie": 25,
					"singapour": 18,
					"russie": 25,
					"monaco": 18,
					"barhein": 25,
					"abudhabi": 25,				
				},
				"promotion": "NOT USED"
			}
		]
	}
]